{
  "$schema": "https://developer.microsoft.com/json-schemas/fabric/item/report/definition/visualContainer/2.1.0/schema.json",
  "name": "0de9e2423461d0a81e00",
  "position": {
    "x": 184.09090909090909,
    "y": 203.40909090909091,
    "z": 7000,
    "height": 85.227272727272734,
    "width": 86.36363636363636,
    "tabOrder": 7000
  },
  "visual": {
    "visualType": "slicer",
    "query": {
      "queryState": {
        "Values": {
          "projections": [
            {
              "field": {
                "Column": {
                  "Expression": {
                    "SourceRef": {
                      "Entity": "Top Products"
                    }
                  },
                  "Property": "Top Products"
                }
              },
              "queryRef": "Top Products.Top Products",
              "nativeQueryRef": "Top Products",
              "active": true,
              "format": "0"
            }
          ]
        }
      }
    },
    "objects": {
      "data": [
        {
          "properties": {
            "numericStart": {
              "expr": {
                "Literal": {
                  "Value": "3D"
                }
              }
            },
            "mode": {
              "expr": {
                "Literal": {
                  "Value": "'Single'"
                }
              }
            }
          }
        }
      ],
      "general": [
        {
          "properties": {
            "orientation": {
              "expr": {
                "Literal": {
                  "Value": "0D"
                }
              }
            },
            "filter": {
              "filter": {
                "Version": 2,
                "From": [
                  {
                    "Name": "t",
                    "Entity": "Top Products",
                    "Type": 0
                  }
                ],
                "Where": [
                  {
                    "Condition": {
                      "Comparison": {
                        "ComparisonKind": 0,
                        "Left": {
                          "Column": {
                            "Expression": {
                              "SourceRef": {
                                "Source": "t"
                              }
                            },
                            "Property": "Top Products"
                          }
                        },
                        "Right": {
                          "Literal": {
                            "Value": "3D"
                          }
                        }
                      }
                    }
                  }
                ]
              }
            }
          }
        }
      ],
      "selection": [
        {
          "properties": {
            "strictSingleSelect": {
              "expr": {
                "Literal": {
                  "Value": "false"
                }
              }
            }
          }
        }
      ],
      "numericInputStyle": [
        {
          "properties": {
            "fontFamily": {
              "expr": {
                "Literal": {
                  "Value": "'Arial'"
                }
              }
            },
            "bold": {
              "expr": {
                "Literal": {
                  "Value": "true"
                }
              }
            },
            "textSize": {
              "expr": {
                "Literal": {
                  "Value": "20D"
                }
              }
            },
            "background": {
              "solid": {
                "color": {
                  "expr": {
                    "ThemeDataColor": {
                      "ColorId": 0,
                      "Percent": -0.1
                    }
                  }
                }
              }
            },
            "fontColor": {
              "solid": {
                "color": {
                  "expr": {
                    "ThemeDataColor": {
                      "ColorId": 3,
                      "Percent": 0
                    }
                  }
                }
              }
            }
          }
        }
      ],
      "header": [
        {
          "properties": {
            "show": {
              "expr": {
                "Literal": {
                  "Value": "false"
                }
              }
            },
            "fontFamily": {
              "expr": {
                "Literal": {
                  "Value": "'Arial'"
                }
              }
            },
            "text": {
              "expr": {
                "Literal": {
                  "Value": "'Type here:'"
                }
              }
            },
            "bold": {
              "expr": {
                "Literal": {
                  "Value": "false"
                }
              }
            },
            "background": {
              "solid": {
                "color": {
                  "expr": {
                    "ThemeDataColor": {
                      "ColorId": 0,
                      "Percent": -0.1
                    }
                  }
                }
              }
            },
            "fontColor": {
              "solid": {
                "color": {
                  "expr": {
                    "ThemeDataColor": {
                      "ColorId": 1,
                      "Percent": 0
                    }
                  }
                }
              }
            }
          }
        }
      ],
      "slider": [
        {
          "properties": {
            "show": {
              "expr": {
                "Literal": {
                  "Value": "false"
                }
              }
            },
            "color": {
              "solid": {
                "color": {
                  "expr": {
                    "ThemeDataColor": {
                      "ColorId": 1,
                      "Percent": 0
                    }
                  }
                }
              }
            }
          }
        }
      ]
    },
    "visualContainerObjects": {
      "background": [
        {
          "properties": {
            "show": {
              "expr": {
                "Literal": {
                  "Value": "true"
                }
              }
            },
            "color": {
              "solid": {
                "color": {
                  "expr": {
                    "ThemeDataColor": {
                      "ColorId": 0,
                      "Percent": -0.1
                    }
                  }
                }
              }
            },
            "transparency": {
              "expr": {
                "Literal": {
                  "Value": "80D"
                }
              }
            }
          }
        }
      ],
      "border": [
        {
          "properties": {
            "show": {
              "expr": {
                "Literal": {
                  "Value": "false"
                }
              }
            }
          }
        }
      ],
      "title": [
        {
          "properties": {
            "show": {
              "expr": {
                "Literal": {
                  "Value": "true"
                }
              }
            },
            "fontFamily": {
              "expr": {
                "Literal": {
                  "Value": "'Arial'"
                }
              }
            },
            "text": {
              "expr": {
                "Literal": {
                  "Value": "'Type here:'"
                }
              }
            },
            "fontSize": {
              "expr": {
                "Literal": {
                  "Value": "8D"
                }
              }
            },
            "bold": {
              "expr": {
                "Literal": {
                  "Value": "true"
                }
              }
            },
            "alignment": {
              "expr": {
                "Literal": {
                  "Value": "'center'"
                }
              }
            }
          }
        }
      ]
    },
    "syncGroup": {
      "groupName": "Top Products",
      "fieldChanges": true,
      "filterChanges": true
    },
    "drillFilterOtherVisuals": true
  }
}